odoo/addons/pms_l10n_es_sii/README.rst
odoo/addons/pms_l10n_es_sii/__init__.py
odoo/addons/pms_l10n_es_sii/__manifest__.py
odoo/addons/pms_l10n_es_sii/data/pms_data.xml
odoo/addons/pms_l10n_es_sii/i18n/pms_l10n_es_sii.pot
odoo/addons/pms_l10n_es_sii/readme/CONTRIBUTORS.rst
odoo/addons/pms_l10n_es_sii/readme/DESCRIPTION.rst
odoo/addons/pms_l10n_es_sii/readme/USAGE.rst
odoo/addons/pms_l10n_es_sii/static/description/icon.png
odoo/addons/pms_l10n_es_sii/static/description/index.html
odoo14_addon_pms_l10n_es_sii-14.0.1.1.0.dist-info/METADATA
odoo14_addon_pms_l10n_es_sii-14.0.1.1.0.dist-info/WHEEL
odoo14_addon_pms_l10n_es_sii-14.0.1.1.0.dist-info/top_level.txt
odoo14_addon_pms_l10n_es_sii-14.0.1.1.0.dist-info/RECORD
